finance_insight/__init__.py
finance_insight/fin_insight.py
fin_insight-0.1.2.dist-info/LICENSE
fin_insight-0.1.2.dist-info/METADATA
fin_insight-0.1.2.dist-info/WHEEL
fin_insight-0.1.2.dist-info/entry_points.txt
fin_insight-0.1.2.dist-info/top_level.txt
fin_insight-0.1.2.dist-info/RECORD
