Metadata-Version: 2.2
Name: fin-insight
Version: 0.1.2
Summary: A financial analysis tool for stock sentiment and rating
Author-email: Spock Stein <spockstein@example.com>
License: MIT License
Project-URL: Homepage, https://github.com/spockstein/fin_insight
Classifier: Development Status :: 3 - Alpha
Classifier: Intended Audience :: Developers
Classifier: Intended Audience :: Financial and Insurance Industry
Classifier: License :: OSI Approved :: MIT License
Classifier: Operating System :: OS Independent
Classifier: Programming Language :: Python :: 3
Classifier: Programming Language :: Python :: 3.8
Classifier: Programming Language :: Python :: 3.9
Classifier: Programming Language :: Python :: 3.10
Classifier: Topic :: Software Development :: Libraries :: Python Modules
Classifier: Topic :: Office/Business :: Financial :: Investment
Requires-Python: >=3.8
License-File: LICENSE
Requires-Dist: yfinance>=0.2.38
Requires-Dist: requests>=2.31.0
Requires-Dist: vaderSentiment>=3.3.2
Requires-Dist: pandas>=1.3
Provides-Extra: dev
Requires-Dist: pytest>=7.4.4; extra == "dev"
Requires-Dist: twine>=4.0.2; extra == "dev"
